dhedge/__init__.py
dhedge/exchange_rates.py
dhedge/factory.py
dhedge/pool.py
dhedge/token.py
dhedge/utills.py
dhedge/abi/__init__.py
dhedge/abi/address_resolver.py
dhedge/abi/exchange_rates.py
dhedge/abi/factory.py
dhedge/abi/pool.py
dhedge/abi/token.py
dhedge-0.0.1.dist-info/LICENSE
dhedge-0.0.1.dist-info/METADATA
dhedge-0.0.1.dist-info/WHEEL
dhedge-0.0.1.dist-info/top_level.txt
dhedge-0.0.1.dist-info/RECORD
