Metadata-Version: 2.1
Name: dhedge
Version: 0.0.1
Summary: dHedge.org Trading Python SDK
Home-page: https://github.com/NikitaPirate/dhedge-python-sdk
Author: NikitaPirate
Author-email: spasepirat@gmail.com
License: UNKNOWN
Platform: UNKNOWN
